Metadata-Version: 2.1
Name: NoCodeTextClassifier
Version: 0.0.5
Summary: This package is for Text Classification of NLP Task
Home-page: https://github.com/Al-Hasib/NoCodeTextClassifier
Author: abdullah
Author-email: alhasib.iu.cse@gmail.com
Classifier: Programming Language :: Python :: 3
Classifier: License :: OSI Approved :: MIT License
Classifier: Operating System :: OS Independent
Requires-Python: >=3.8
License-File: LICENSE
Requires-Dist: pandas
Requires-Dist: scikit-learn
Requires-Dist: matplotlib
Requires-Dist: seaborn
Requires-Dist: pathlib
Requires-Dist: nltk
Requires-Dist: xgboost
